README.md
setup.py
lagan/__init__.py
lagan/lagan.py
micropython_lagan.egg-info/PKG-INFO
micropython_lagan.egg-info/SOURCES.txt
micropython_lagan.egg-info/dependency_links.txt
micropython_lagan.egg-info/top_level.txt