Metadata-Version: 2.1
Name: micropython-lagan
Version: 1.2
Summary: log system
Home-page: https://github.com/jdhxyy/lagan-micropython
Author: jdh99
Author-email: jdh821@163.com
License: UNKNOWN
Platform: UNKNOWN
